techlens_agent/__init__.py
techlens_agent/agent.py
techlens_agent/code_scan.py
techlens_agent/config.py
techlens_agent/upload.py
techlens_agent/user.py
techlens_agent/cloud/cloud_dataclass.py
techlens_agent/cloud/aws/blocks.py
techlens_agent/cloud/aws/costs.py
techlens_agent/cloud/aws/get_profile.py
techlens_agent/cloud/aws/instances.py
techlens_agent/cloud/aws/regions.py
techlens_agent/cloud/azure/blocks.py
techlens_agent/cloud/azure/cloud_helper.py
techlens_agent/cloud/azure/costs.py
techlens_agent/cloud/azure/instances.py
techlens_agent/cloud/gcp/blocks.py
techlens_agent/cloud/gcp/instances.py
techlens_agent/cloud/gcp/zones.py
techlens_agent/dependencies/walk.py
techlens_agent/dependencies/walkers/README.md
techlens_agent/dependencies/walkers/classes.py
techlens_agent/dependencies/walkers/composer.py
techlens_agent/dependencies/walkers/dockerwalker.py
techlens_agent/dependencies/walkers/gemwalker.py
techlens_agent/dependencies/walkers/go.py
techlens_agent/dependencies/walkers/maven.py
techlens_agent/dependencies/walkers/npm.py
techlens_agent/dependencies/walkers/nuget.py
techlens_agent/dependencies/walkers/package_lock.py
techlens_agent/dependencies/walkers/python.py
techlens_agent/system/__init__.py
techlens_agent/system/sysinfo.py
techlens_agent/templates/results.j2
techlens_agent/utils/git_metrics.py
techlens_agent/utils/utils.py
techlens_agent-0.6.5.dist-info/METADATA
techlens_agent-0.6.5.dist-info/WHEEL
techlens_agent-0.6.5.dist-info/entry_points.txt
techlens_agent-0.6.5.dist-info/licenses/LICENSE
techlens_agent-0.6.5.dist-info/RECORD
