Metadata-Version: 2.4
Name: techlens-agent
Version: 0.6.5
Summary: This tool safely and securely analyzes applications for benchmarking.
Project-URL: Homepage, https://github.com/corsis-tech/techlens-agent
Project-URL: Bug Tracker, https://github.com/corsis-tech/techlens-agent/issues
Project-URL: Source, https://github.com/corsis-tech/techlens-agent
Author-email: Crosslake Technologies <techlens@crosslaketech.com>
License-File: LICENSE
Classifier: License :: Free for non-commercial use
Classifier: Programming Language :: Python :: 3
Requires-Python: <=3.14,>=3.10
Requires-Dist: azure-identity~=1.25.1
Requires-Dist: azure-mgmt-compute~=37.0.0
Requires-Dist: azure-mgmt-monitor~=7.0.0
Requires-Dist: azure-mgmt-network~=29.0.0
Requires-Dist: azure-mgmt-resource~=24.0.0
Requires-Dist: azure-mgmt-storage~=24.0.0
Requires-Dist: azure-monitor-query~=1.4.0
Requires-Dist: boto3~=1.40.7
Requires-Dist: defusedxml~=0.7.1
Requires-Dist: gemfileparser~=0.8.0
Requires-Dist: google-cloud-compute>=1.14.0
Requires-Dist: google-cloud-monitoring>=2.15.0
Requires-Dist: google-cloud-storage>=2.10.0
Requires-Dist: httpx[http2]~=0.28.1
Requires-Dist: jinja2==3.1.6
Requires-Dist: johnnydep~=1.20.6
Requires-Dist: psutil~=7.1.0
Requires-Dist: pyyaml~=6.0.2
Requires-Dist: semgrep==1.139.0
Requires-Dist: setuptools<81
Requires-Dist: techlens-metrics==0.3.0
Requires-Dist: techlens-pygments-tsx==0.3.0
Requires-Dist: windows-curses~=2.4.0; sys_platform == 'win32'
Provides-Extra: dev
Requires-Dist: black>=24.1.1; extra == 'dev'
Requires-Dist: coverage; extra == 'dev'
Requires-Dist: pytest; extra == 'dev'
Requires-Dist: pytest-cov; extra == 'dev'
Requires-Dist: pytest-xdist; extra == 'dev'
